SubFoldersProject/__init__.py
SubFoldersProject/sfp.py
SubFoldersProject/examples/example1_generator/example1_generator.py
SubFoldersProject/examples/example1_generator/platform.png
SubFoldersProject/examples/example1_generator/platform2.png
SubFoldersProject/examples/example2_txt_and_csv/example2_txt_csv.py
SubFoldersProject/examples/example2_txt_and_csv/platform.png
SubFoldersProject/examples/example2_txt_and_csv/platform2.png
SubFoldersProject/examples/example2_txt_and_csv/temp.txt
SubFoldersProject/examples/example2_txt_and_csv/test.csv
SubFoldersProject/examples/example3_tmx/desert.tsx
SubFoldersProject/examples/example3_tmx/desert1.tmx
SubFoldersProject/examples/example3_tmx/example3_tmx.py
SubFoldersProject/examples/example3_tmx/temp.txt
SubFoldersProject/examples/example3_tmx/tmw_desert_spacing.png
SubFoldersProject/examples/example4_camera/desert.tmx
SubFoldersProject/examples/example4_camera/desert.tsx
SubFoldersProject/examples/example4_camera/example4_camera.py
SubFoldersProject/examples/example4_camera/platform.png
SubFoldersProject/examples/example4_camera/platform2.png
SubFoldersProject/examples/example4_camera/temp.txt
SubFoldersProject/examples/example4_camera/tmw_desert_spacing.png
SubFoldersProject-1.0.0.dist-info/LICENSE
SubFoldersProject-1.0.0.dist-info/METADATA
SubFoldersProject-1.0.0.dist-info/WHEEL
SubFoldersProject-1.0.0.dist-info/top_level.txt
SubFoldersProject-1.0.0.dist-info/RECORD
